{"cameraMode":{"drawMode":0,"name":"Shaded","section":"Shading Mode"},"sceneLighting":true,"audioPlay":false,"sceneViewState":{"m_AlwaysRefresh":false,"showFog":true,"showSkybox":true,"showFlares":true,"showImageEffects":true,"showParticleSystems":true,"showVisualEffectGraphs":true,"m_FxEnabled":true},"in2DMode":false,"pivot":{"x":-91.23619842529297,"y":11.721304893493653,"z":574.6942138671875},"rotation":{"x":0.25145813822746279,"y":0.09682775288820267,"z":-0.02442517876625061,"w":0.963101863861084},"size":36.143577575683597,"orthographic":false}